unreal_blender_mcp/__init__.py
unreal_blender_mcp/langchain_integration.py
unreal_blender_mcp/prompt_examples.py
unreal_blender_mcp/prompts.py
unreal_blender_mcp/server.py
unreal_blender_mcp/unreal_connection.py
unreal_blender_mcp/ai_tools/__init__.py
unreal_blender_mcp/ai_tools/prompt_engineering.py
unreal_blender_mcp/ai_tools/tool_definitions.py
unreal_blender_mcp/ai_tools/tool_handler.py
unreal_blender_mcp/blender_addon/README.md
unreal_blender_mcp/blender_addon/__init__.py
unreal_blender_mcp/blender_addon/extended_addon.py
unreal_blender_mcp/blender_addon/interface.py
unreal_blender_mcp/blender_addon_server/README.md
unreal_blender_mcp/blender_addon_server/__init__.py
unreal_blender_mcp/blender_addon_server/extended_server.py
unreal_blender_mcp/blender_addon_server/interface.py
mseep_unreal_blender_mcp-0.1.1.dist-info/METADATA
mseep_unreal_blender_mcp-0.1.1.dist-info/WHEEL
mseep_unreal_blender_mcp-0.1.1.dist-info/entry_points.txt
mseep_unreal_blender_mcp-0.1.1.dist-info/RECORD
